Workbook

Sheet Dashboard
B9: DASHBOARD DE PLANEJAMENTO FINANCEIRO E INDEPENDÊNCIA
B12: PATRIMÔNIO REAL (30 ANOS) | E12: RENDA MENSAL REAL (30 ANOS) | H12: RENDIMENTO REAL MENSAL
B13: ='Calculadora Financeira'!D39 -> 1708059.1 | E13: ='Calculadora Financeira'!E39 -> 11063.661 | H13: ='Calculadora Financeira'!D14 -> 0.0064773293
B35: COMO USAR ESTE DASHBOARD:
B36: 1. Vá na aba 'Calculadora Financeira' para alterar seus dados (Salário, Aporte, Taxas).
B37: 2. Selecione seu Perfil de Investidor na aba da Calculadora.
B38: 3. Os gráficos e indicadores acima serão atualizados automaticamente.

Sheet Alocação Estratégica
A1: CHAVE | B1: PERFIL | C1: TIPO DE FII | D1: PERCENTUAL
A2: Conservador-PAPEL | B2: Conservador | C2: PAPEL | D2: 0.3
A3: Conservador-TIJOLO | B3: Conservador | C3: TIJOLO | D3: 0.5
A4: Conservador-HÍBRIDOS | B4: Conservador | C4: HÍBRIDOS | D4: 0.1
A5: Conservador-FOFs | B5: Conservador | C5: FOFs | D5: 0.1
A6: Conservador-DESENVOLVIMENTO | B6: Conservador | C6: DESENVOLVIMENTO | D6: 0
A7: Conservador-HOTELARIAS | B7: Conservador | C7: HOTELARIAS | D7: 0
A8: Moderado-PAPEL | B8: Moderado | C8: PAPEL | D8: 0.32
A9: Moderado-TIJOLO | B9: Moderado | C9: TIJOLO | D9: 0.35
A10: Moderado-HÍBRIDOS | B10: Moderado | C10: HÍBRIDOS | D10: 0.08
A11: Moderado-FOFs | B11: Moderado | C11: FOFs | D11: 0.05
A12: Moderado-DESENVOLVIMENTO | B12: Moderado | C12: DESENVOLVIMENTO | D12: 0.1
A13: Moderado-HOTELARIAS | B13: Moderado | C13: HOTELARIAS | D13: 0.1
... A19: Agressivo-HOTELARIAS | B19: Agressivo | C19: HOTELARIAS | D19: 0.1

Sheet Calculadora Financeira
B9: VARIÁVEIS DE ENTRADA
B10: Salário Mensal | D10: 6000
B11: Rendimento Mensal Nominal (%) | D11: 0.01
B12: Inflação Mensal Estimada (%) | D12: 0.0035
B13: % de Investimento Sugerido | D13: 0.2
B14: Taxa Real Mensal (Fisher) | D14: =((1+D11)/(1+D12))-1 -> 0.0064773293
B16: INVESTIMENTO MENSAL
B17: Valor a Investir por Mês | D17: =D10*D13 -> 1200
B18: Tempo (Anos) | D18: 5
B20: RESULTADOS (PODER DE COMPRA REAL)
B21: Patrimônio Acumulado Real | D21: =FV(D14, D18*12, -D17) -> 87652.002
B22: Dividendos Mensais Reais | D22: =D21*D14 -> 567.75089
B24: ALOCAÇÃO ESTRATÉGICA EM FIIs
B25: Perfil Selecionado: | C25: Conservador
B26: TIPO | C26: Percentual (%) | D26: Valor
B27: PAPEL | C27: =VLOOKUP($C$25&"-"&B27, 'Alocação Estratégica'!$A$2:$D$19, 4, FALSE) -> 0.3 | D27: =C27*$D$17 -> 360
B28: TIJOLO | C28: =VLOOKUP($C$25&"-"&B28, 'Alocação Estratégica'!$A$2:$D$19, 4, FALSE) -> 0.5 | D28: =C28*$D$17 -> 600
B29: HÍBRIDOS | C29: =VLOOKUP($C$25&"-"&B29, 'Alocação Estratégica'!$A$2:$D$19, 4, FALSE) -> 0.1 | D29: =C29*$D$17 -> 120
B30: FOFs | C30: =VLOOKUP($C$25&"-"&B30, 'Alocação Estratégica'!$A$2:$D$19, 4, FALSE) -> 0.1 | D30: =C30*$D$17 -> 120
B31: DESENVOLVIMENTO | C31: =VLOOKUP($C$25&"-"&B31, 'Alocação Estratégica'!$A$2:$D$19, 4, FALSE) -> 0 | D31: =C31*$D$17 -> 0
B32: HOTELARIAS | C32: =VLOOKUP($C$25&"-"&B32, 'Alocação Estratégica'!$A$2:$D$19, 4, FALSE) -> 0 | D32: =C32*$D$17 -> 0
B34: Cenários (Anos) | C34: Patrimônio (Nominal) | D34: Patrimônio Real | E34: Dividendos Mensais (Reais)
B35: 2 | C35: =FV($D$11, B35*12, -$D$17) -> 32368.158 | D35: =FV($D$14, B35*12, -$D$17) -> 31050.751 | E35: =D35*$D$14 -> 201.12594
B36: 5 | C36: =FV($D$11, B36*12, -$D$17) -> 98003.604 | D36: =FV($D$14, B36*12, -$D$17) -> 87652.002 | E36: =D36*$D$14 -> 567.75089
B37: 10 | C37: =FV($D$11, B37*12, -$D$17) -> 276046.43 | D37: =FV($D$14, B37*12, -$D$17) -> 216774.42 | E37: =D37*$D$14 -> 1404.1193
B38: 20 | C38: =FV($D$11, B38*12, -$D$17) -> 1187106.4 | D38: =FV($D$14, B38*12, -$D$17) -> 687196.48 | E38: =D38*$D$14 -> 4451.1979
B39: 30 | C39: =FV($D$11, B39*12, -$D$17) -> 4193957 | D39: =FV($D$14, B39*12, -$D$17) -> 1708059.1 | E39: =D39*$D$14 -> 11063.661
